pto_common_timesheet_mfdenison_hopkinsep/__init__.py
pto_common_timesheet_mfdenison_hopkinsep/database.py
pto_common_timesheet_mfdenison_hopkinsep/models.py
pto_common_timesheet_mfdenison_hopkinsep/utils/__init__.py
pto_common_timesheet_mfdenison_hopkinsep/utils/dashboard_events.py
pto_common_timesheet_mfdenison_hopkinsep/utils/pto_update_manager.py
pto_common_timesheet_mfdenison_hopkinsep-0.0.2.dist-info/METADATA
pto_common_timesheet_mfdenison_hopkinsep-0.0.2.dist-info/WHEEL
pto_common_timesheet_mfdenison_hopkinsep-0.0.2.dist-info/top_level.txt
pto_common_timesheet_mfdenison_hopkinsep-0.0.2.dist-info/RECORD
