Metadata-Version: 2.4
Name: pto_common_timesheet_mfdenison_hopkinsep
Version: 0.0.2
Summary: Common models and utilities for PTO management
Author: Mathew Denison
Requires-Dist: sqlmodel>=0.0.6
Requires-Dist: pydantic
Dynamic: author
Dynamic: requires-dist
Dynamic: summary
